spktype01.py
spktype01-1.0.0.dist-info/LICENSE.txt
spktype01-1.0.0.dist-info/METADATA
spktype01-1.0.0.dist-info/WHEEL
spktype01-1.0.0.dist-info/top_level.txt
spktype01-1.0.0.dist-info/RECORD
