Metadata-Version: 2.1
Name: spktype01
Version: 1.0.0
Summary: A supporting module for jplephem to handle data type 1
Home-page: https://github.com/whiskie14142/spktype01
Author: whiskie14142
Author-email: whiskie14142@gmail.com
License: MIT
Keywords: jplephem SPK type1
Platform: UNKNOWN
Classifier: Development Status :: 5 - Production/Stable
Classifier: Programming Language :: Python :: 3
Classifier: License :: OSI Approved :: MIT License
Classifier: Operating System :: OS Independent
